controller/__init__.py
controller/controller.py
controller/mobile.py
controller-0.1.0.dist-info/LICENSE
controller-0.1.0.dist-info/METADATA
controller-0.1.0.dist-info/WHEEL
controller-0.1.0.dist-info/top_level.txt
controller-0.1.0.dist-info/RECORD
