Metadata-Version: 2.1
Name: controller
Version: 0.1.0
Summary: Enables connection to ControllerApp
Home-page: https://www.controllerapp.ml
Author: Faruk Hammoud
Author-email: farukhammoud@student-cs.fr
License: UNKNOWN
Platform: UNKNOWN
Classifier: Programming Language :: Python :: 3
Classifier: License :: OSI Approved :: MIT License
Classifier: Operating System :: OS Independent
Requires-Python: >=3.6
